LICENSE
MANIFEST.in
README.md
requirements.txt
setup.py
ezcharts/__init__.py
ezcharts/demo.py
ezcharts/ond_demo.py
ezcharts/ont_demo.py
ezcharts/util.py
ezcharts.egg-info/PKG-INFO
ezcharts.egg-info/SOURCES.txt
ezcharts.egg-info/dependency_links.txt
ezcharts.egg-info/entry_points.txt
ezcharts.egg-info/not-zip-safe
ezcharts.egg-info/requires.txt
ezcharts.egg-info/top_level.txt
ezcharts/components/__init__.py
ezcharts/components/bcfstats.py
ezcharts/components/clinvar.py
ezcharts/components/common.py
ezcharts/components/details.py
ezcharts/components/dss.py
ezcharts/components/ezchart.py
ezcharts/components/fastcat.py
ezcharts/components/lead_summary.py
ezcharts/components/modkit.py
ezcharts/components/mosdepth.py
ezcharts/components/nextclade.py
ezcharts/components/params.py
ezcharts/components/plotmetadata.py
ezcharts/components/status.py
ezcharts/components/theme.py
ezcharts/components/value_displays.py
ezcharts/components/versions.py
ezcharts/components/reports/__init__.py
ezcharts/components/reports/comp.py
ezcharts/components/reports/labs.py
ezcharts/components/reports/ond.py
ezcharts/components/reports/ont.py
ezcharts/data/icons/circle-check-solid-sage.svg
ezcharts/data/icons/circle-check-solid-white.svg
ezcharts/data/icons/circle-exclamation-solid-red.svg
ezcharts/data/icons/circle-exclamation-solid-white.svg
ezcharts/data/icons/circle-minus-solid-neutral-cool.svg
ezcharts/data/icons/circle-minus-solid-white.svg
ezcharts/data/images/LAB_logo.svg
ezcharts/data/images/OND_logo.svg
ezcharts/data/images/OND_logo.txt
ezcharts/data/images/ONT_logo.svg
ezcharts/data/images/ONT_logo.txt
ezcharts/data/images/ONT_logo_white.svg
ezcharts/data/reference/hg19/cytoBand.txt.gz
ezcharts/data/reference/hg19/hg19.chrom.sizes.gz
ezcharts/data/reference/hg38/cytoBand.txt.gz
ezcharts/data/reference/hg38/hg38.chrom.sizes.gz
ezcharts/data/scripts/epi2melabs.js
ezcharts/data/scripts/metagenomics-sankey-util.js
ezcharts/data/scripts/metagenomics-sankey.js
ezcharts/data/scripts/nextclade.html
ezcharts/data/scripts/ond.js
ezcharts/data/scripts/ont.js
ezcharts/data/styles/epi2melabs.scss
ezcharts/data/styles/metagenomics-sankey.css
ezcharts/data/styles/ond.scss
ezcharts/data/styles/ont.scss
