Metadata-Version: 2.4
Name: ezcharts
Version: 0.15.2
Summary: eCharts plotting API.
Home-page: https://github.com/epi2me-labs/ezcharts
Author: cwright
Author-email: cwright@nanoporetech.com
License-File: LICENSE
Requires-Dist: bokeh~=3.1.0
Requires-Dist: dominate
Requires-Dist: jinja2
Requires-Dist: libsass
Requires-Dist: numpy
Requires-Dist: pandas
Requires-Dist: pydantic<2.0.0
Requires-Dist: scipy
Requires-Dist: seaborn~=0.12.0
Requires-Dist: sigfig
Requires-Dist: natsort==8.4.0
Requires-Dist: pysam
Requires-Dist: pymsaviz==0.5.0
Requires-Dist: biopython==1.86
Requires-Dist: setuptools
Requires-Dist: si-prefix==1.3.3
Dynamic: author
Dynamic: author-email
Dynamic: description
Dynamic: description-content-type
Dynamic: home-page
Dynamic: license-file
Dynamic: requires-dist
Dynamic: summary
